logzio/__init__.py
logzio/exceptions.py
logzio/flusher.py
logzio/handler.py
logzio/logger.py
logzio/sender.py
logzio_python_handler-4.1.9.dist-info/licenses/LICENSE
tests/__init__.py
tests/test_add_context.py
tests/test_extra_fields.py
tests/test_logzioHandler.py
tests/test_logzioSender.py
tests/test_thread_safety.py
tests/e2e/__init__.py
tests/e2e/test_logzio_e2e.py
tests/mockLogzioListener/__init__.py
tests/mockLogzioListener/listener.py
tests/mockLogzioListener/logsList.py
tests/mockLogzioListener/persistentFlags.py
logzio_python_handler-4.1.9.dist-info/METADATA
logzio_python_handler-4.1.9.dist-info/WHEEL
logzio_python_handler-4.1.9.dist-info/top_level.txt
logzio_python_handler-4.1.9.dist-info/RECORD
